{
    "configurations": [
        {
            "name": "ISIXRTOS",
            "includePath": [ 		"${workspaceFolder}/isixrtos/libfoundation/include",
		"${workspaceFolder}/isixrtos/libisix/include",
		"${workspaceFolder}/isixrtos/libisix/arch/arm/include",
		"${workspaceFolder}/isixrtos/libisix/arch/arm/cortexm/m4f/include",
		"${workspaceFolder}/isixrtos/libisix/arch/arm/cortexm/include",
		"${workspaceFolder}/isixrtos/libisix/arch/include",
		"${workspaceFolder}/isixrtos/config/include",
		"${workspaceFolder}/isixrtos/libperiph/periph/include",
		"${workspaceFolder}/isixrtos/libperiph/vendor/arm/cortexm/stm32/f4/include",
		"${workspaceFolder}/isixrtos/libperiph/periph/include/arch/arm/cortexm/stm32",
		"${workspaceFolder}/isixrtos/libperiph/periph/include/arch/arm/cortexm/stm32/f4",
		"${workspaceFolder}/isixrtos/libperiph/vendor/arm/cortexm/cmsis/include",
		"${workspaceFolder}/isixrtos/libperiph/vendor/arm/cortexm/cmsis/device/stm32/f4/include",
		"${workspaceFolder}/stm32f469i_disco/board/include",
		"${workspaceFolder}/stm32f469i_disco/e0_led_blink",
		"${workspaceFolder}/stm32f469i_disco/e1_graphics",
		"${workspaceFolder}/isixrtos/libgfx/include",
		"${workspaceFolder}/build/isixrtos/libisix/include"
             ],
            "defines": [ 			"PDEBUG",
			"STM32MCU_MAJOR_TYPE_F4=1",
			"STM32F469xx",
			"USE_FULL_LL_DRIVER=1",
			"HSE_VALUE=8000000",
			"CONFIG_ISIX_USE_TIMERS=1",
			"HAVE_ISIX_CONFIG_H=1"
             ],
            "compilerPath": "/usr/bin/arm-none-eabi-g++",
			"compilerArgs": ["-mcpu=cortex-m4", "-mthumb", "-std=gnu++17",
							  "-mfloat-abi=hard", "-mfpu=fpv4-sp-d16", "-ffast-math", 
							  "-fsingle-precision-constant", "-Wno-variadic-macros", 
							  "-Wno-long-long", "-Wno-pragma-once-outside-header" ],
            "cStandard": "c11",
            "cppStandard": "c++17",
            "intelliSenseMode": "gcc-x86"
        }
    ],
    "version": 4
}
